autoCLI_config/__init__.py
autoCLI_config/config_param.py
autoCLI_config/decorators.py
autoCLI_config/parser.py
autoCLI_config/utils.py
autocli_config-0.1.6.dist-info/licenses/LICENSE
autocli_config-0.1.6.dist-info/METADATA
autocli_config-0.1.6.dist-info/WHEEL
autocli_config-0.1.6.dist-info/top_level.txt
autocli_config-0.1.6.dist-info/RECORD
