Metadata-Version: 2.4
Name: autoCLI_config
Version: 0.1.6
Summary: Automatic configuration management and documentation generation system
Home-page: https://github.com/rsanchezgarc/autoCLI_config
Author: Ruben Sanchez-Garcia
Author-email: Ruben Sanchez-Garcia <rsanchezgarcia@faculty.ie.edu>
License: GPL-3.0-or-later
Project-URL: Homepage, https://github.com/rsanchezgarc/autoCLI_config
Project-URL: Bug Reports, https://github.com/rsanchezgarc/autoCLI_config/issues
Project-URL: Source, https://github.com/rsanchezgarc/autoCLI_config
Keywords: configuration,cli,documentation,argparse,dataclass
Classifier: Development Status :: 3 - Alpha
Classifier: Intended Audience :: Developers
Classifier: Topic :: Software Development :: Libraries :: Python Modules
Classifier: License :: OSI Approved :: GNU General Public License v3 (GPLv3)
Classifier: Programming Language :: Python :: 3
Classifier: Programming Language :: Python :: 3.9
Classifier: Programming Language :: Python :: 3.10
Classifier: Programming Language :: Python :: 3.11
Classifier: Programming Language :: Python :: 3.12
Classifier: Programming Language :: Python :: 3.13
Requires-Python: >=3.9
License-File: LICENSE
Requires-Dist: argParseFromDoc>=0.0.8
Requires-Dist: PyYAML>=5.1
Provides-Extra: dev
Requires-Dist: pytest>=6.0; extra == "dev"
Requires-Dist: pytest-cov>=2.0; extra == "dev"
Dynamic: author
Dynamic: home-page
Dynamic: license-file
Dynamic: requires-python
